src/__init__.py
src/main.py
src/tests/__init__.py
src/tests/board_test.py
src/tests/game_test.py
src/tests/player_test.py
src/tic_tac_toe/__init__.py
src/tic_tac_toe/board.py
src/tic_tac_toe/board_renderer.py
src/tic_tac_toe/game.py
src/tic_tac_toe/player.py
TTT_CLI-1.0.dist-info/METADATA
TTT_CLI-1.0.dist-info/WHEEL
TTT_CLI-1.0.dist-info/entry_points.txt
TTT_CLI-1.0.dist-info/top_level.txt
TTT_CLI-1.0.dist-info/RECORD
