Metadata-Version: 2.1
Name: TTT-CLI
Version: 1.0
Summary: A simple TicTacToe CLI game in Python
Author: Thomas Lo
